textual_riff/__about__.py
textual_riff/__init__.py
textual_riff/entry_points.py
textual_riff/riff.tcss
textual_riff-0.1.dist-info/METADATA
textual_riff-0.1.dist-info/WHEEL
textual_riff-0.1.dist-info/entry_points.txt
textual_riff-0.1.dist-info/licenses/LICENSE.txt
textual_riff-0.1.dist-info/RECORD
